BetterDesign/__init__.py
BetterDesign/design/BetterDesign.py
BetterDesign/design/__init__.py
BetterDesign-2.0.0.dist-info/LICENSE
BetterDesign-2.0.0.dist-info/METADATA
BetterDesign-2.0.0.dist-info/WHEEL
BetterDesign-2.0.0.dist-info/top_level.txt
BetterDesign-2.0.0.dist-info/RECORD
