Metadata-Version: 2.1
Name: BetterDesign
Version: 2.0.0
Summary: Used to make your design of terminal apps easier!
Author: convict
License: MIT
Project-URL: GitHub, https://github.com/c0nvict/BetterDesign
Platform: UNKNOWN
Classifier: Development Status :: 4 - Beta
Classifier: License :: OSI Approved :: MIT License
Classifier: Programming Language :: Python :: 3
Requires-Python: >=3.8
License-File: LICENSE
